orka_vector_api/__init__.py
orka_vector_api/logging_config.py
orka_vector_api/orka_db.py
orka_vector_api/swagger_config.py
orka_vector_api/enums/__init__.py
orka_vector_api/enums/status.py
orka_vector_api/exceptions/__init__.py
orka_vector_api/exceptions/orka.py
orka_vector_api/helper/__init__.py
orka_vector_api/helper/gdal_helper.py
orka_vector_api/helper/job_helper.py
orka_vector_api/views/__init__.py
orka_vector_api/views/data.py
orka_vector_api/views/jobs.py
orka_vector_api/views/status.py
orka_vector_api-0.1.0.dist-info/LICENSE
orka_vector_api-0.1.0.dist-info/METADATA
orka_vector_api-0.1.0.dist-info/WHEEL
orka_vector_api-0.1.0.dist-info/top_level.txt
orka_vector_api-0.1.0.dist-info/RECORD
