Metadata-Version: 2.1
Name: orka-vector-api
Version: 0.1.0
Summary: Rest API for orka vector data
Home-page: https://github.com/terrestris/OrKa-Vector-API
Author: Jan Suleiman @ terrestris GmbH & Co. KG
Author-email: info@terrestris.de
License: Apache-2.0
Platform: UNKNOWN
Requires-Dist: PyYAML (~=5.4.1)
Requires-Dist: flasgger (~=0.9.5)
Requires-Dist: flask (~=1.1.2)
Requires-Dist: psycopg2 (~=2.8.6)
Requires-Dist: requests (~=2.25.1)
Requires-Dist: uuid (~=1.30)
